AUTHORS.rst
CHANGES.rst
LICENSE
MANIFEST.in
README.rst
setup.py
Envelopes.egg-info/PKG-INFO
Envelopes.egg-info/SOURCES.txt
Envelopes.egg-info/dependency_links.txt
Envelopes.egg-info/not-zip-safe
Envelopes.egg-info/top_level.txt
docs/.gitignore
docs/Makefile
docs/conf.py
docs/index.rst
docs/make.bat
docs/_build/.DS_Store
docs/api/conn.rst
docs/api/connstack.rst
docs/api/envelope.rst
docs/examples/celery.rst
docs/examples/flask.rst
envelopes/__init__.py
envelopes/compat.py
envelopes/conn.py
envelopes/connstack.py
envelopes/envelope.py
envelopes/local.py
examples/__init__.py
examples/__init__.pyc
examples/example_celery.py
examples/example_flask.py
lib/__init__.py
lib/__init__.pyc
lib/testing.py
lib/testing.pyc
tests/test_conn.py
tests/test_conn.pyc
tests/test_envelope.py
tests/test_envelope.pyc